{"name":"MDK-ARM","type":"ARM","mode":"simple_7inches","toolchain":"AC5","dependenceList":[{"groupName":"custom","depList":[{"name":"default","sourceDirList":[],"libList":[],"incList":[".\\..\\Drivers\\STM32F4xx_HAL_Driver\\Inc",".\\..\\Drivers\\STM32F4xx_HAL_Driver\\Inc\\Legacy",".\\..\\Drivers\\CMSIS\\Device\\ST\\STM32F4xx\\Include",".\\..\\Drivers\\CMSIS\\Include",".\\..\\Core\\User\\app\\common\\inc",".\\..\\Core\\User\\app\\system\\inc",".\\..\\Core\\User\\boot\\Inc",".\\..\\Core\\User\\doc",".\\..\\Core\\User\\lib",".\\..\\Core\\User\\lib\\bspLib\\inc",".\\..\\Core\\User\\lib\\bspLib\\usb\\FATFS\\inc",".\\..\\Core\\User\\lib\\bspLib\\usb\\STM32_USB_OTG_Driver\\inc",".\\..\\Core\\User\\lib\\bspLib\\usb\\STM32_USB_HOST_Library\\Class\\MSC\\inc",".\\..\\Core\\User\\lib\\bspLib\\usb\\STM32_USB_HOST_Library\\Core\\inc",".\\..\\Core\\User\\lib\\bspLib\\usb\\USB_APP",".\\..\\Core\\User\\lib\\doPTLib\\inc",".\\.eide\\deps"],"defineList":["STM32F429_439xx","USE_USB_OTG_FS","APPLICACION","USE_STDPERIPH_DRIVER","SYSTEM1","STM32F429xx"]}]}],"compileConfig":{"cpuType":"Cortex-M4","floatingPointHardware":"single","useCustomScatterFile":false,"scatterFilePath":"undefined","storageLayout":{"RAM":[{"tag":"RAM","id":1,"mem":{"startAddr":"","size":""},"isChecked":false,"noInit":false},{"tag":"RAM","id":2,"mem":{"startAddr":"","size":""},"isChecked":false,"noInit":false},{"tag":"RAM","id":3,"mem":{"startAddr":"","size":""},"isChecked":false,"noInit":false},{"tag":"IRAM","id":1,"mem":{"startAddr":"0x20000080","size":"0x2FF80"},"isChecked":true,"noInit":false},{"tag":"IRAM","id":2,"mem":{"startAddr":"0x10000000","size":"0x00010000"},"isChecked":true,"noInit":false}],"ROM":[{"tag":"ROM","id":1,"mem":{"startAddr":"","size":""},"isChecked":false,"isStartup":false},{"tag":"ROM","id":2,"mem":{"startAddr":"","size":""},"isChecked":false,"isStartup":false},{"tag":"ROM","id":3,"mem":{"startAddr":"","size":""},"isChecked":false,"isStartup":false},{"tag":"IROM","id":1,"mem":{"startAddr":"0x08000000","size":"0x00100000"},"isChecked":true,"isStartup":true},{"tag":"IROM","id":2,"mem":{"startAddr":"","size":""},"isChecked":false,"isStartup":false}]},"options":"null"},"uploader":"STLink","srcDirs":[".\\.eide\\deps"],"virtualFolder":[{"name":"::CMSIS","files":[],"folders":[]},{"name":"Application","files":[],"folders":[{"name":"MDK-ARM","files":[{"path":".\\startup_stm32f429xx.s"}],"folders":[]},{"name":"lib","files":[{"path":".\\..\\Core\\User\\lib\\cpulib.lib"},{"path":".\\..\\Core\\User\\lib\\doptlib.lib"}],"folders":[]},{"name":"fun","files":[{"path":".\\..\\Core\\User\\app\\common\\src\\communication.c"},{"path":".\\..\\Core\\User\\app\\common\\src\\exfunction.c"},{"path":".\\..\\Core\\User\\app\\common\\src\\flashsave.c"},{"path":".\\..\\Core\\User\\app\\common\\src\\function.c"},{"path":".\\..\\Core\\User\\app\\common\\src\\lcddisp.c"},{"path":".\\..\\Core\\User\\app\\common\\src\\Mit_funtion.c"},{"path":".\\..\\Core\\User\\app\\common\\src\\Mit_menu_files.c"},{"path":".\\..\\Core\\User\\app\\common\\src\\Patfun.c"},{"path":".\\..\\Core\\User\\app\\common\\src\\register.c"},{"path":".\\..\\Core\\User\\app\\common\\src\\ScrollBar.c"},{"path":".\\..\\Core\\User\\app\\common\\src\\Toast.c"},{"path":".\\..\\Core\\User\\app\\common\\src\\upflash.c"},{"path":".\\..\\Core\\User\\app\\common\\src\\msgpic.c"},{"path":".\\..\\Core\\User\\app\\common\\inc\\color.h"},{"path":".\\..\\Core\\User\\app\\common\\inc\\integer.h"},{"path":".\\..\\Core\\User\\app\\common\\inc\\menu.h"},{"path":".\\..\\Core\\User\\app\\common\\inc\\register.h"},{"path":".\\..\\Core\\User\\app\\common\\inc\\title.h"}],"folders":[]},{"name":"sys","files":[{"path":".\\..\\Core\\User\\boot\\Src\\main.c"},{"path":".\\..\\Core\\User\\boot\\Src\\systemMain.c"},{"path":".\\..\\Core\\User\\boot\\Src\\utility.c"}],"folders":[]},{"name":"doc","files":[{"path":".\\..\\Core\\User\\doc\\readme.txt"}],"folders":[]},{"name":"app","files":[{"path":".\\..\\Core\\User\\app\\system\\src\\menu_convert.c"},{"path":".\\..\\Core\\User\\app\\system\\src\\menu_create.c"},{"path":".\\..\\Core\\User\\app\\system\\src\\menu_documents.c"},{"path":".\\..\\Core\\User\\app\\system\\src\\menu_function.c"},{"path":".\\..\\Core\\User\\app\\system\\src\\menu_help.c"},{"path":".\\..\\Core\\User\\app\\system\\src\\menu_iotest.c"},{"path":".\\..\\Core\\User\\app\\system\\src\\menu_modify.c"},{"path":".\\..\\Core\\User\\app\\system\\src\\menu_p.c"},{"path":".\\..\\Core\\User\\app\\system\\src\\menu_program.c"},{"path":".\\..\\Core\\User\\app\\system\\src\\viewPattern.c"}],"folders":[]}]},{"name":"Drivers","files":[],"folders":[{"name":"CMSIS","files":[{"path":".\\..\\Core\\User\\boot\\Src\\system_stm32f4xx.c"}],"folders":[]}]}],"excludeList":[],"outDir":".\\build","deviceName":"STM32F429IGTx","packDir":".\\pack\\Keil\\STM32F4xx_DFP.2.13.0","uploadConfig":{"bin":".\\build\\simple_7inches\\MDK-ARM.hex","proType":"SWD","runAfterProgram":true,"speed":4000,"address":"0x08000000","elFile":"None","optionBytes":".eide/simple_7inches.st.option.bytes.ini"},"miscInfo":{"uid":"3315c8f4dcb40fcdfaebd9302b6f704e"},"targets":{"simple_7inches":{"compileConfig":{"cpuType":"Cortex-M4","floatingPointHardware":"single","useCustomScatterFile":false,"scatterFilePath":"undefined","storageLayout":{"RAM":[{"tag":"RAM","id":1,"mem":{"startAddr":"0x0","size":"0x0"},"isChecked":false,"noInit":false},{"tag":"RAM","id":2,"mem":{"startAddr":"0x0","size":"0x0"},"isChecked":false,"noInit":false},{"tag":"RAM","id":3,"mem":{"startAddr":"0x0","size":"0x0"},"isChecked":false,"noInit":false},{"tag":"IRAM","id":1,"mem":{"startAddr":"0x20000080","size":"0x2ff80"},"isChecked":true,"noInit":false},{"tag":"IRAM","id":2,"mem":{"startAddr":"0x10000000","size":"0x10000"},"isChecked":true,"noInit":false}],"ROM":[{"tag":"ROM","id":1,"mem":{"startAddr":"0x0","size":"0x0"},"isChecked":false,"isStartup":false},{"tag":"ROM","id":2,"mem":{"startAddr":"0x0","size":"0x0"},"isChecked":false,"isStartup":false},{"tag":"ROM","id":3,"mem":{"startAddr":"0x0","size":"0x0"},"isChecked":false,"isStartup":false},{"tag":"IROM","id":1,"mem":{"startAddr":"0x8000000","size":"0x100000"},"isChecked":true,"isStartup":true},{"tag":"IROM","id":2,"mem":{"startAddr":"0x0","size":"0x0"},"isChecked":false,"isStartup":false}]},"options":"null"},"uploader":"JLink","uploadConfig":{"bin":"null","baseAddr":"0x08000000","cpuInfo":{"vendor":"ST","cpuName":"STM32F103C8"},"proType":1,"speed":8000},"toolchain":"AC5","custom_dep":{"name":"default","sourceDirList":[],"libList":[],"incList":[".\\..\\Core\\Inc",".\\..\\Drivers\\STM32F4xx_HAL_Driver\\Inc",".\\..\\Drivers\\STM32F4xx_HAL_Driver\\Inc\\Legacy",".\\..\\Drivers\\CMSIS\\Device\\ST\\STM32F4xx\\Include",".\\..\\Drivers\\CMSIS\\Include",".\\..\\Core\\User\\app\\common\\inc",".\\..\\Core\\User\\app\\system\\inc",".\\..\\Core\\User\\boot\\Inc",".\\..\\Core\\User\\doc",".\\..\\Core\\User\\lib",".\\..\\Core\\User\\lib\\bspLib\\inc",".\\..\\Core\\User\\lib\\bspLib\\usb\\FATFS\\inc",".\\..\\Core\\User\\lib\\bspLib\\usb\\STM32_USB_OTG_Driver\\inc",".\\..\\Core\\User\\lib\\bspLib\\usb\\STM32_USB_HOST_Library\\Class\\MSC\\inc",".\\..\\Core\\User\\lib\\bspLib\\usb\\STM32_USB_HOST_Library\\Core\\inc",".\\..\\Core\\User\\lib\\bspLib\\usb\\USB_APP",".\\..\\Core\\User\\lib\\doPTLib\\inc"],"defineList":["STM32F429_439xx","USE_USB_OTG_FS","APPLICACION","USE_STDPERIPH_DRIVER","SYSTEM1","STM32F429xx"]},"excludeList":[]}},"version":"2.6"}